celeryt/__init__.py
celeryt/celeryt.py
celeryt/cli.py
celeryt/ressources/celery.json
celeryt/ressources/common.json
celeryt/ressources/skinos.json
celeryt-0.9.9.dist-info/METADATA
celeryt-0.9.9.dist-info/WHEEL
celeryt-0.9.9.dist-info/entry_points.txt
celeryt-0.9.9.dist-info/top_level.txt
celeryt-0.9.9.dist-info/RECORD
