Metadata-Version: 2.1
Name: celeryt
Version: 0.9.9
Summary: UNKNOWN
Home-page: UNKNOWN
Author: diggersheep
Author-email: alexandre.combeau@outlook.fr
Maintainer: diggersheep
Maintainer-email: alexandre.combeau@outlook.fr
License: PSF
Keywords: celery,skinos,project builder,unistra,Université de Strasbourg
Platform: UNKNOWN
Requires-Dist: docopt (<1.0.0,>=0.6.2)
Requires-Dist: jinja2 (<3.0.0,>=2.11.2)
